{
  "schema_version": 1,
  "bundle_id": "recipient-init-command-message-transition-evidence-bundle",
  "reviewed_at": "2026-05-17",
  "purpose": "Tie one executable recipient init command-message transition to its claim, proof certificate, schematic trace, rendered SVG, and source-status boundaries.",
  "claim_id": "UC-RECIPIENT-INIT-COMMAND-MESSAGE-PROCESSED",
  "predicate": "recipient_init_command_message_processed",
  "positive_example": "fixed upstream wire right init processed",
  "transition_function": "step_fixed_cell",
  "expected_status": "recipient-init-command-message-processed",
  "artifacts": {
    "claim_manifest": "claims/transition_claims.json",
    "proof_certificates": "claims/proof_certificates.json",
    "schematic_trace": "schematics/recipient_init_command_message_trace.json",
    "schematic_svg": "schematics/recipient_init_command_message_trace.svg",
    "hardware_witness_map": "sources/prc_hardware_witness_map.json",
    "source_statuses": [
      "sources/command_semantics_gaps.json",
      "sources/proflog_frontier_status.json",
      "sources/proflog_pin.json"
    ]
  },
  "boundaries": [
    "This bundle covers only init-family recipient command-message consumption.",
    "Non-init recipient command messages remain rejected or blocked by source-status records.",
    "standard-signal command-token execution remains blocked per command_semantics_gaps.",
    "write-buffer command-token execution is implemented on recipient and self paths per command_semantics_gaps.",
    "SJAS formal-confidence is integrated via proflog_pin.json, not blocked on missing Proflog frontier."
  ]
}
